netsim/__init__.py
netsim/common.py
netsim/py.typed
netsim/topology-defaults.yml
netsim/ansible/collect-configs.ansible
netsim/ansible/config.ansible
netsim/ansible/create-config.ansible
netsim/ansible/device-ready.ansible
netsim/ansible/initial-config.ansible
netsim/ansible/missing.yml
netsim/ansible/reload-config.ansible
netsim/ansible/tasks/create-config.yml
netsim/ansible/tasks/create-custom-config.yml
netsim/ansible/tasks/deploy-custom-config.yml
netsim/ansible/tasks/deploy-module.yml
netsim/ansible/tasks/initial-config.yml
netsim/ansible/tasks/wait-for-ready.yml
netsim/ansible/tasks/deploy-config/arcos.yml
netsim/ansible/tasks/deploy-config/arubacx.yml
netsim/ansible/tasks/deploy-config/asa.yml
netsim/ansible/tasks/deploy-config/cumulus.yml
netsim/ansible/tasks/deploy-config/cumulus_nvue.yml
netsim/ansible/tasks/deploy-config/dellos10.yml
netsim/ansible/tasks/deploy-config/eos.yml
netsim/ansible/tasks/deploy-config/fortinet.fortios.fortios.yml
netsim/ansible/tasks/deploy-config/frr.yml
netsim/ansible/tasks/deploy-config/ios.yml
netsim/ansible/tasks/deploy-config/iosxr.yml
netsim/ansible/tasks/deploy-config/junos.yml
netsim/ansible/tasks/deploy-config/linux-clab.yml
netsim/ansible/tasks/deploy-config/linux.yml
netsim/ansible/tasks/deploy-config/missing.yml
netsim/ansible/tasks/deploy-config/netscaler.yml
netsim/ansible/tasks/deploy-config/none.yml
netsim/ansible/tasks/deploy-config/nxos.yml
netsim/ansible/tasks/deploy-config/openbsd.yml
netsim/ansible/tasks/deploy-config/routeros.yml
netsim/ansible/tasks/deploy-config/routeros7.yml
netsim/ansible/tasks/deploy-config/sonic.yml
netsim/ansible/tasks/deploy-config/srlinux.yml
netsim/ansible/tasks/deploy-config/sros.yml
netsim/ansible/tasks/deploy-config/vyos-script.j2
netsim/ansible/tasks/deploy-config/vyos.yml
netsim/ansible/tasks/fetch-config/_config_cleanup.j2
netsim/ansible/tasks/fetch-config/arcos.yml
netsim/ansible/tasks/fetch-config/arubacx.yml
netsim/ansible/tasks/fetch-config/asa.yml
networklab-26.1.1.dist-info/licenses/LICENSE.md
networklab-26.1.1.dist-info/METADATA
networklab-26.1.1.dist-info/WHEEL
networklab-26.1.1.dist-info/top_level.txt
networklab-26.1.1.dist-info/RECORD
