Metadata-Version: 2.4
Name: networklab
Version: 26.1.1
Summary: CLI-based Virtual Networking Lab Abstraction Layer
Home-page: https://github.com/ipspace/netlab
Author: Ivan Pepelnjak
Author-email: ip@ipspace.net
Classifier: Topic :: Utilities
Classifier: Programming Language :: Python
Classifier: Programming Language :: Python :: 3
Classifier: Programming Language :: Python :: 3.8
Classifier: Programming Language :: Python :: 3.9
Classifier: Programming Language :: Python :: 3.10
Classifier: Programming Language :: Python :: 3.11
Classifier: Programming Language :: Python :: 3.12
Classifier: Programming Language :: Python :: 3.13
Classifier: Programming Language :: Python :: 3.14
Classifier: Operating System :: POSIX :: Linux
Classifier: Operating System :: MacOS
Requires-Python: >=3.8
License-File: LICENSE.md
Requires-Dist: Jinja2>=3.1.4
Requires-Dist: PyYAML>=5.0.0
Requires-Dist: netaddr>=0.8.0
Requires-Dist: python-box!=7.3.1,~=7.2
Requires-Dist: importlib_resources
Requires-Dist: typing-extensions>=4.3.0
Requires-Dist: filelock>=3.16.1
Requires-Dist: packaging
Requires-Dist: requests
Requires-Dist: rich
Dynamic: author
Dynamic: author-email
Dynamic: classifier
Dynamic: description
Dynamic: description-content-type
Dynamic: home-page
Dynamic: license-file
Dynamic: requires-dist
Dynamic: requires-python
Dynamic: summary
